xrscipy/__init__.py
xrscipy/docs.py
xrscipy/errors.py
xrscipy/fft.py
xrscipy/fftpack.py
xrscipy/integrate.py
xrscipy/utils.py
xrscipy/signal/__init__.py
xrscipy/signal/filters.py
xrscipy/signal/spectral.py
xrscipy/signal/utils.py
xrscipy-3.1.0.dist-info/METADATA
xrscipy-3.1.0.dist-info/WHEEL
xrscipy-3.1.0.dist-info/top_level.txt
xrscipy-3.1.0.dist-info/RECORD
