Metadata-Version: 2.4
Name: xrscipy
Version: 3.1.0
Summary: Scipy integrated into xarray
Author-email: xarray Developers <xarray@googlegroups.com>
License-Expression: Apache-2.0
Project-URL: Repository, https://github.com/hippalectryon-0/xr-scipy
Project-URL: Documentation, https://xr-scipy.readthedocs.io
Classifier: Development Status :: 4 - Beta
Classifier: Operating System :: OS Independent
Classifier: Intended Audience :: Science/Research
Classifier: Programming Language :: Python :: 3.9
Classifier: Programming Language :: Python :: 3.10
Classifier: Programming Language :: Python :: 3.11
Classifier: Programming Language :: Python :: 3.12
Classifier: Programming Language :: Python :: 3.13
Classifier: Topic :: Scientific/Engineering
Requires-Python: <4,>=3.9
Requires-Dist: scipy>=1.9
Requires-Dist: xarray>=0.16
Requires-Dist: docstring-parser>=0.15
